{
  "2024-10-23": {
    "eventname": "✕"
  },
  "2024-10-25": {
    "eventname": "✕"
  },
  "2024-10-26": {
    "eventname": "池ハロ",
    "url": "https://x.com/98tml/status/1838153692677071309"
  },
  "2024-10-30": {
    "eventname": "✕"
  },
  "2024-10-31": {
    "eventname": "✕<br>確定"
  },
  "2024-11-01": {
    "eventname": "✕<br>確定"
  },
  "2024-11-02": {
    "eventname": "✕<br>確定"
  },
  "2024-11-04": {
    "eventname": "✕<br>確定"
  },
  "2024-11-18": {
    "eventname": "✕<br>確定"
  },
  "2024-11-27": {
    "eventname": "✕<br>未定"
  },
  "2024-12-25": {
    "eventname": "✕"
  },
  "2024-12-28": {
    "eventname": "✕<br>コミケ設営"
  },
  "2024-12-29": {
    "eventname": "冬コミ(一般)"
  },
  "2024-12-30": {
    "eventname": "冬コミ(サークル)"
  },
  "2024-12-31": {
    "eventname": "✕"
  },
  "2025-01-01": {
    "eventname": "✕"
  },
  "2025-01-02": {
    "eventname": "✕"
  },
  "2025-01-03": {
    "eventname": "○"
  },
  "2025-01-12": {
    "eventname": "✕<br>確定"
  },
  "2024-12-07": {
    "eventname": "a!池袋(仮)"
  },
  "2024-12-08": {
    "eventname": "a!池袋(仮)"
  },
  "2025-04-26": {
    "eventname": "超会議"
  },
  "2025-04-27": {
    "eventname": "超会議"
  }
}